json_literal/__init__.py
json_literal-1.1.0.dist-info/METADATA
json_literal-1.1.0.dist-info/WHEEL
json_literal-1.1.0.dist-info/RECORD
